setup.py
HeapqDict/__init__.py
HeapqDict/heapqdict.py
heapqdict_nhannht.egg-info/PKG-INFO
heapqdict_nhannht.egg-info/SOURCES.txt
heapqdict_nhannht.egg-info/dependency_links.txt
heapqdict_nhannht.egg-info/not-zip-safe
heapqdict_nhannht.egg-info/top_level.txt