Metadata-Version: 2.1
Name: heapqdict-nhannht
Version: 0.1
Summary: wrapper of heapq that work on dict
Home-page: UNKNOWN
License: UNKNOWN
Platform: UNKNOWN
